bootstrap/__init__.py
bootstrap/config.py
bootstrap/crypto_tools.py
bootstrap/keychain_register.py
bootstrap/types.py
bootstrap/app/__init__.py
bootstrap/app/controller.py
bootstrap/app/entity.py
bootstrap/ndnauth/__init__.py
bootstrap/ndnauth/auth_state.py
bootstrap/ndnauth/mode_encoder.py
bootstrap/ndnauth/name_assigner.py
bootstrap/ndnauth/protocol.py
bootstrap/ndnauth/app/__init__.py
bootstrap/ndnauth/app/name_aa.py
bootstrap/ndnauth/app/name_requester.py
bootstrap/ndnauth/name_auth/__init__.py
bootstrap/ndnauth/name_auth/authenticate.py
bootstrap/ndnauth/name_auth/authenticate_server.py
bootstrap/ndnauth/name_auth/authenticate_user.py
bootstrap/ndnauth/name_auth/member_check.py
bootstrap/ndnauth/name_auth/member_check_server.py
bootstrap/ndnauth/name_auth/member_check_user.py
bootstrap/ndncert/__init__.py
bootstrap/ndncert/cert_state.py
bootstrap/ndncert/challenge_encoder.py
bootstrap/ndncert/possession_verifier.py
bootstrap/ndncert/protocol_v3.py
bootstrap/ndncert/verifier.py
bootstrap/ndncert/app/__init__.py
bootstrap/ndncert/app/cert_issuer.py
bootstrap/ndncert/app/cert_requester.py
ndn_bootstrap-0.1.post2.dist-info/COPYING
ndn_bootstrap-0.1.post2.dist-info/METADATA
ndn_bootstrap-0.1.post2.dist-info/WHEEL
ndn_bootstrap-0.1.post2.dist-info/top_level.txt
ndn_bootstrap-0.1.post2.dist-info/RECORD
